<?xml version="1.0"?>
<!DOCTYPE hibernate-mapping PUBLIC "-//Hibernate/Hibernate Mapping DTD 3.0//EN"
"http://www.hibernate.org/dtd/hibernate-mapping-3.0.dtd">
<!-- Generated 14-may-2014 3:10:36 by Hibernate Tools 3.6.0 -->
<hibernate-mapping>
    <class name="appcostal.model.Procesion" table="procesion" catalog="appcostal">
        <id name="idprocesion" type="java.lang.Integer">
            <column name="idprocesion" />
            <generator class="identity" />
        </id>
        <many-to-one name="recorrido" class="appcostal.model.Recorrido" fetch="select">
            <column name="idrecorrido" not-null="true" />
        </many-to-one>
        <many-to-one name="paso" class="appcostal.model.Paso" fetch="select">
            <column name="idpaso" not-null="true" />
        </many-to-one>
        <property name="descripcion" type="string">
            <column name="descripcion" length="45" />
        </property>
        <property name="fecha" type="timestamp">
            <column name="fecha" length="19" not-null="true" />
        </property>
        <property name="esensayo" type="boolean">
            <column name="esensayo" not-null="true" />
        </property>
        <set name="relevos" table="relevo" inverse="true" lazy="true" fetch="select">
            <key>
                <column name="idprocesion" not-null="true" />
            </key>
            <one-to-many class="appcostal.model.Relevo" />
        </set>
    </class>
</hibernate-mapping>
